setup.py
SimpleTkGUIKit/SimpleTkGUIKit.py
SimpleTkGUIKit/__init__.py
SimpleTkGUIKit.egg-info/PKG-INFO
SimpleTkGUIKit.egg-info/SOURCES.txt
SimpleTkGUIKit.egg-info/dependency_links.txt
SimpleTkGUIKit.egg-info/top_level.txt