Metadata-Version: 1.0
Name: SimpleTkGUIKit
Version: 0.0.2
Summary: Simple GUI kit with python Tkinter
Home-page: https://github.com/AtsushiSakai/SimpleTkGUIKit
Author: Atsushi Sakai
Author-email: asakai.amsl@gmail.com
License: MIT
Keywords: google earth plot kml
Platform: UNKNOWN
